handright/__init__.py
handright/_core.py
handright/_exceptions.py
handright/_template.py
handright/_util.py
handright-8.2.0.dist-info/LICENSE.txt
handright-8.2.0.dist-info/METADATA
handright-8.2.0.dist-info/WHEEL
handright-8.2.0.dist-info/top_level.txt
handright-8.2.0.dist-info/zip-safe
handright-8.2.0.dist-info/RECORD
