Metadata-Version: 2.1
Name: handright
Version: 8.2.0
Summary: A lightweight Python library for simulating Chinese handwriting
Home-page: https://github.com/Gsllchb/Handright
Author: Chenghui Li (Gsllchb)
Author-email: Gsllchb@qq.com
License: bsd-3-clause
Keywords: simulating Chinese handwriting
Platform: UNKNOWN
Classifier: Programming Language :: Python :: 3.8
Classifier: Programming Language :: Python :: 3.9
Classifier: Programming Language :: Python :: 3.10
Classifier: Programming Language :: Python :: 3.11
Classifier: Programming Language :: Python :: Implementation :: CPython
Requires-Python: >= 3.8
License-File: LICENSE.txt
